celeryanalytics_housekeeping/__init__.py
celeryanalytics_housekeeping/app_settings.py
celeryanalytics_housekeeping/apps.py
celeryanalytics_housekeeping/tasks.py
allianceauth_celeryanalytics_housekeeping-0.0.1a4.dist-info/LICENSE
allianceauth_celeryanalytics_housekeeping-0.0.1a4.dist-info/METADATA
allianceauth_celeryanalytics_housekeeping-0.0.1a4.dist-info/WHEEL
allianceauth_celeryanalytics_housekeeping-0.0.1a4.dist-info/top_level.txt
allianceauth_celeryanalytics_housekeeping-0.0.1a4.dist-info/RECORD
